gha_update/__init__.py
gha_update/__main__.py
gha_update/_cli.py
gha_update/_core.py
gha_update/py.typed
gha_update-0.1.0.dist-info/entry_points.txt
gha_update-0.1.0.dist-info/LICENSE.txt
gha_update-0.1.0.dist-info/WHEEL
gha_update-0.1.0.dist-info/METADATA
gha_update-0.1.0.dist-info/RECORD
