Metadata-Version: 2.1
Name: gha-update
Version: 0.1.0
Summary: Update GitHub Actions version pins in GitHub workflow files.
Author: David Lord
Requires-Python: >=3.12
Requires-Dist: click
Requires-Dist: httpx
